{
  "iterations": [
    {
      "iteration": 1,
      "startedAt": "2026-04-22T02:18:42.468Z",
      "endedAt": "2026-04-22T02:18:49.686Z",
      "durationMs": 5420,
      "agent": "codex",
      "model": "",
      "toolsUsed": {},
      "filesModified": [],
      "exitCode": 1,
      "completionDetected": false,
      "errors": [
        "API error: API error 400: {\"error\":{\"message\":\"\\\"auto\\\" tool choice requires --enable-auto-tool-choice and --tool-call-parser to be set\",\"type\":\"BadRequestError\",\"param\":null,\"code\":400}}"
      ]
    }
  ],
  "totalDurationMs": 5420,
  "struggleIndicators": {
    "repeatedErrors": {
      "API error: API error 400: {\"error\":{\"message\":\"\\\"auto\\\" tool choice requires --enable-auto-tool-choi": 1
    },
    "noProgressIterations": 1,
    "shortIterations": 1
  }
}