{
  "iterations": [
    {
      "iteration": 1,
      "startedAt": "2026-04-25T02:12:20.031Z",
      "endedAt": "2026-04-25T02:28:58.850Z",
      "durationMs": 997067,
      "agent": "codex",
      "model": "",
      "toolsUsed": {},
      "filesModified": [
        "schema/registry/compile-pipelines/chatbot-compile.yaml",
        "server/src/compiler/pipeline/PipelineRunner.ts",
        "server/src/compiler/pipeline/chatbotCompilePipelineLoad.test.ts",
        "server/src/compiler/artifacts/",
        "server/src/compiler/pipeline/PipelineWhenEvaluation.test.ts",
        "server/src/compiler/validation/"
      ],
      "exitCode": 0,
      "completionDetected": false,
      "errors": []
    }
  ],
  "totalDurationMs": 997067,
  "struggleIndicators": {
    "repeatedErrors": {},
    "noProgressIterations": 0,
    "shortIterations": 0
  }
}